document_qa/document_qa_engine.py
document_qa/grobid_processors.py
document_qa/langchain.py
document_qa/ner_client_generic.py
document_qa/deployment/modal_inference.py
document_qa_engine-0.5.1.dist-info/METADATA
document_qa_engine-0.5.1.dist-info/WHEEL
document_qa_engine-0.5.1.dist-info/top_level.txt
document_qa_engine-0.5.1.dist-info/RECORD
