Metadata-Version: 2.4
Name: document-qa-engine
Version: 0.5.1
Summary: Scientific Document Insight Q/A
Author-email: Luca Foppiano <lucanoro@duck.com>
Maintainer-email: Luca Foppiano <lucanoro@duck.com>
License:                                  Apache License
Project-URL: Homepage, https://document-insights.streamlit.app
Project-URL: Repository, https://github.com/lfoppiano/document-qa
Project-URL: Changelog, https://github.com/lfoppiano/document-qa/blob/main/CHANGELOG.md
Requires-Dist: grobid-quantities-client==0.4.0
Requires-Dist: grobid-client-python==0.0.9
Requires-Dist: grobid-tei-xml==0.1.3
Requires-Dist: tqdm==4.66.3
Requires-Dist: pyyaml==6.0.1
Requires-Dist: pytest==8.1.1
Requires-Dist: streamlit==1.45.1
Requires-Dist: lxml==5.2.1
Requires-Dist: beautifulsoup4==4.12.3
Requires-Dist: python-dotenv==1.0.1
Requires-Dist: watchdog==4.0.0
Requires-Dist: dateparser==1.2.0
Requires-Dist: requests>=2.31.0
Requires-Dist: numpy==1.26.4
Requires-Dist: chromadb==0.4.24
Requires-Dist: tiktoken==0.9.0
Requires-Dist: openai==1.82.0
Requires-Dist: langchain==0.3.25
Requires-Dist: langchain-core==0.3.61
Requires-Dist: langchain-openai==0.3.18
Requires-Dist: langchain-huggingface==0.2.0
Requires-Dist: langchain-community==0.3.21
Requires-Dist: typing-inspect==0.9.0
Requires-Dist: typing_extensions==4.12.2
Requires-Dist: pydantic==2.10.6
Requires-Dist: sentence-transformers==2.6.1
Requires-Dist: streamlit-pdf-viewer==0.0.22rc0
Requires-Dist: umap-learn==0.5.6
Requires-Dist: plotly==5.20.0
